H2H_Creator_startgg/H2HCreator.py
H2H_Creator_startgg/__init__.py
H2H_Creator_startgg/api.py
H2H_Creator_startgg/creator.py
H2H_Creator_startgg/events.py
H2H_Creator_startgg/exceptions.py
H2H_Creator_startgg/players.py
H2H_Creator_startgg/queries.py
H2H_Creator_startgg/results.py
H2H_Creator_startgg/spreadsheets.py
H2H_Creator_startgg-0.4.2.1.dist-info/LICENSE
H2H_Creator_startgg-0.4.2.1.dist-info/METADATA
H2H_Creator_startgg-0.4.2.1.dist-info/WHEEL
H2H_Creator_startgg-0.4.2.1.dist-info/top_level.txt
H2H_Creator_startgg-0.4.2.1.dist-info/RECORD
