Metadata-Version: 2.1
Name: H2H-Creator-startgg
Version: 0.4.2.1
Summary: H2H Spreadsheet Creator for startgg
Author: odds_or_evans
Author-email: ETossed <jthroughs@gmail.com>
Project-URL: Homepage, https://github.com/ETossed/H2H-Creator-startgg
Project-URL: Bug Tracker, https://github.com/ETossed/H2H-Creator-startgg/issues
Classifier: Programming Language :: Python :: 3
Classifier: License :: OSI Approved :: MIT License
Classifier: Operating System :: OS Independent
Requires-Python: >=3.7
License-File: LICENSE
